LICENSE
MANIFEST.in
README.rst
setup.py
bin/patchcli
patchlib/__init__.py
patchlib/cli.py
patchlib/exc.py
patchlib/models.py
patchlib.egg-info/PKG-INFO
patchlib.egg-info/SOURCES.txt
patchlib.egg-info/dependency_links.txt
patchlib.egg-info/not-zip-safe
patchlib.egg-info/requires.txt
patchlib.egg-info/top_level.txt
patchlib/api/__init__.py
patchlib/api/community_patch.py
patchlib/api/patch_server.py
patchlib/api/shared.py
patchlib/patch/__init__.py
patchlib/resources/__init__.py
patchlib/resources/schema_full_definition.json
patchlib/resources/schema_version.json