Metadata-Version: 1.2
Name: patchlib
Version: 0.3.0
Summary: A command line tool for Jamf Pro patch definition management.
Home-page: https://github.com/brysontyrrell/PatchCLI
Author: Bryson Tyrrell
Author-email: bryson.tyrrell@gmail.com
License: MIT
Platform: UNKNOWN
Classifier: Development Status :: 3 - Alpha
Classifier: License :: OSI Approved :: MIT License
Classifier: Programming Language :: Python
Classifier: Programming Language :: Python :: 2.7
Classifier: Topic :: Utilities
Requires-Python: >=2.7
